pyateos/__init__.py
pyateos/pyateos.py
pyateos/plugins/__init__.py
pyateos/plugins/acl.py
pyateos/plugins/arp.py
pyateos/plugins/as_path.py
pyateos/plugins/bfd.py
pyateos/plugins/bgp_evpn.py
pyateos/plugins/bgp_ipv4.py
pyateos/plugins/interface.py
pyateos/plugins/ip_route.py
pyateos/plugins/lldp.py
pyateos/plugins/mac.py
pyateos/plugins/mlag.py
pyateos/plugins/ntp.py
pyateos/plugins/prefix_list.py
pyateos/plugins/route_map.py
pyateos/plugins/snmp.py
pyateos/plugins/stp.py
pyateos/plugins/vlan.py
pyateos/plugins/vrf.py
pyateos/plugins/vxlan.py
pyateos-1.0.6.data/scripts/pyateos
pyateos-1.0.6.dist-info/LICENSE
pyateos-1.0.6.dist-info/METADATA
pyateos-1.0.6.dist-info/WHEEL
pyateos-1.0.6.dist-info/top_level.txt
pyateos-1.0.6.dist-info/RECORD
