Metadata-Version: 2.1
Name: pyateos
Version: 1.0.6
Summary: python framework to test operational status of an Arista network
Home-page: https://github.com/lvrfrc87/pyATEOS
Author: Federico Olivieri
Author-email: lvrfrc87@gmail.com
License: UNKNOWN
Platform: UNKNOWN
Classifier: Programming Language :: Python :: 3
Classifier: License :: OSI Approved :: MIT License
Classifier: Operating System :: OS Independent
Requires-Python: >=3.6
Requires-Dist: jsondiff (>=1.2.0)
Requires-Dist: pyeapi (>=0.8.3)
Requires-Dist: jmespath (>=0.9.5)
